aiq_insights
