Metadata-Version: 2.1
Name: aiq_insights
Version: 0.1.2
Summary: A Python library for checking common errors in multiple-choice questions (MCQs)
Home-page: https://github.com/Shiva-DS24/aiq_insights
Author: Your Name
Author-email: doctsh@gmail.com
Classifier: Programming Language :: Python :: 3
Classifier: License :: OSI Approved :: MIT License
Classifier: Operating System :: OS Independent
Requires-Python: >=3.6
Requires-Dist: transformers>=4.0.0
Requires-Dist: scipy>=1.5.0
Requires-Dist: torch>=1.9.0
